[
    {
      "id": 1,
      "name": "Xiaomi Watch S1 Pro",
      "product": "https://cdn.cnbj0.fds.api.mi-img.com/b2c-shopapi-pms/pms_1660149947.96451048.jpg",
      "price": "1599 元"
    },
    {
      "id": 2,
      "name": "Redmi 手表 2",
      "product": "https://cdn.cnbj0.fds.api.mi-img.com/b2c-shopapi-pms/pms_1635387575.72049661.jpg",
      "price": "379 元"
    },
    {
      "id": 3,
      "name": "米家充气宝1S",
      "product": "https://cdn.cnbj0.fds.api.mi-img.com/b2c-shopapi-pms/pms_1624611625.40756028.jpg",
      "price": "189 元"
    },
    {
      "id": 4,
      "name": "小米手环7 Pro",
      "product": "https://cdn.cnbj0.fds.api.mi-img.com/b2c-shopapi-pms/pms_1656673888.59622325.png",
      "price": "399 元"
    },
    {
      "id": 5,
      "name": "九号平衡车 改装套件",
      "product": "https://cdn.cnbj0.fds.api.mi-img.com/b2c-shopapi-pms/pms_1560764684.67767333.jpg",
      "price": "2999 元"
    },
    {
      "id": 6,
      "name": "九号平衡车 Plus",
      "product": "https://cdn.cnbj0.fds.api.mi-img.com/b2c-shopapi-pms/pms_1498623949.929117.jpg",
      "price": "3299 元"
    },
    {
      "id": 7,
      "name": "九号卡丁车Pro兰博基尼汽车定制版",
      "product": "https://cdn.cnbj0.fds.api.mi-img.com/b2c-shopapi-pms/pms_1596609066.1477389.jpg",
      "price": "9999 元"
    },
    {
      "id": 8,
      "name": "九号ninebot儿童山地自行车",
      "product": "https://cdn.cnbj0.fds.api.mi-img.com/b2c-shopapi-pms/pms_1638954886.26793946.jpg",
      "price": "949 元"
    },
    {
      "id": 9,
      "name": "Xiaomi Watch S1",
      "product": "https://cdn.cnbj0.fds.api.mi-img.com/b2c-shopapi-pms/pms_1640677355.02633044.png",
      "price": "999 元"
    },
    {
      "id": 10,
      "name": "小米无线车充",
      "product": "https://cdn.cnbj0.fds.api.mi-img.com/b2c-shopapi-pms/pms_1550588698.59891591.jpg",
      "price": "189 元"
    },
    {
      "id": 11,
      "name": "Xiaomi Watch Color 2",
      "product": "https://cdn.cnbj0.fds.api.mi-img.com/b2c-shopapi-pms/pms_1636013466.46185049.png",
      "price": "799 元"
    },
    {
      "id": 12,
      "name": "米家电动滑板车 3 青春版",
      "product": "https://cdn.cnbj0.fds.api.mi-img.com/b2c-shopapi-pms/CE96B9B4B066EE3D4A73E14F033BD38B.png",
      "price": "1799 元"
    }
  ]